spezi_data_pipeline/__init__.py
spezi_data_pipeline/data_access/__init__.py
spezi_data_pipeline/data_access/firebase_fhir_data_access.py
spezi_data_pipeline/data_exploration/__init__.py
spezi_data_pipeline/data_exploration/data_explorer.py
spezi_data_pipeline/data_export/__init__.py
spezi_data_pipeline/data_export/data_exporter.py
spezi_data_pipeline/data_flattening/__init__.py
spezi_data_pipeline/data_flattening/fhir_resources_flattener.py
spezi_data_pipeline/data_processing/__init__.py
spezi_data_pipeline/data_processing/code_mapping.py
spezi_data_pipeline/data_processing/data_processor.py
spezi_data_pipeline/data_processing/observation_processor.py
spezi_data_pipeline/data_processing/questionnaire_processor.py
spezi_data_pipeline-0.1.0.dist-info/METADATA
spezi_data_pipeline-0.1.0.dist-info/WHEEL
spezi_data_pipeline-0.1.0.dist-info/licenses/LICENSE
spezi_data_pipeline-0.1.0.dist-info/RECORD
