Metadata-Version: 2.3
Name: spezi_data_pipeline
Version: 0.1.0
Summary: A comprehensive data pipeline for accessing, downloading, restructuring, processing, and exporting FHIR-compatible health data from cloud storage platforms including Google Firebase.
Author: Vicky Bikia, Paul Schmiedmayer, Adrit Rao, Oliver Aalami
License: MIT License
License-File: LICENSE
Classifier: Development Status :: 4 - Beta
Classifier: Intended Audience :: Healthcare Industry
Classifier: License :: OSI Approved :: MIT License
Classifier: Programming Language :: Python :: 3.8
Classifier: Programming Language :: Python :: 3.9
Classifier: Programming Language :: Python :: 3.10
Classifier: Topic :: Software Development :: Libraries
Requires-Python: >=3.7
Requires-Dist: fhir-resources>=6.0.0
Requires-Dist: firebase-admin>=5.0.0
Requires-Dist: matplotlib>=3.4.0
Requires-Dist: numpy>=1.20.0
Requires-Dist: pandas>=1.3.0
Provides-Extra: dev
Requires-Dist: coverage; extra == 'dev'
Requires-Dist: pytest-cov>=2.10.0; extra == 'dev'
Requires-Dist: pytest>=7.0; extra == 'dev'
